mercadolibre/__init__.py
mercadolibre/_authentication.py
mercadolibre/api.py
mercadolibre/authentication.py
mercadolibre/authorization.py
mercadolibre/category.py
mercadolibre/item.py
mercadolibre/product.py
mercadolibre/review.py
mercadolibre/search.py
mercadolibre/user.py
mercadolibre_sdk-0.0.16.dist-info/METADATA
mercadolibre_sdk-0.0.16.dist-info/WHEEL
mercadolibre_sdk-0.0.16.dist-info/entry_points.txt
mercadolibre_sdk-0.0.16.dist-info/top_level.txt
mercadolibre_sdk-0.0.16.dist-info/RECORD
