Metadata-Version: 2.1
Name: mercadolibre-sdk
Version: 0.0.16
Summary: Description of your package
Home-page: https://github.com/mercadoradar/mercadolibre-sdk
Author: Mercado Radar
Requires-Dist: requests ==2.31.0
Requires-Dist: redis ==5.0.1
Requires-Dist: flask ==3.0.0
Requires-Dist: python-dotenv ==1.0.0
